five.grok-3.0-py3.11-nspkg.pth
five/grok/README.txt
five/grok/__init__.py
five/grok/absoluteurl.py
five/grok/components.py
five/grok/configure.zcml
five/grok/formlib.py
five/grok/ftesting.zcml
five/grok/interfaces.py
five/grok/meta.py
five/grok/meta.zcml
five/grok/overrides.zcml
five/grok/subscribers.py
five/grok/templatereg.py
five/grok/testing.py
five/grok/ftests/__init__.py
five/grok/ftests/test_grok_functional.py
five/grok/ftests/directoryresource/__init__.py
five/grok/ftests/directoryresource/dirresource.py
five/grok/ftests/directoryresource/fixture/__init__.py
five/grok/ftests/directoryresource/fixture/resource.py
five/grok/ftests/directoryresource/fixture/anotherfoo/anotherfile.txt
five/grok/ftests/directoryresource/fixture/anotherfoo/file.txt
five/grok/ftests/directoryresource/fixture/bar/file.txt
five/grok/ftests/directoryresource/fixture/bar/baz/file.txt
five/grok/ftests/directoryresource/fixture/foo/file.txt
five/grok/ftests/form/__init__.py
five/grok/ftests/form/autofields.py
five/grok/ftests/form/autofields2.py
five/grok/ftests/form/form.py
five/grok/ftests/site/__init__.py
five/grok/ftests/site/folder_site.py
five/grok/ftests/site/local_site.py
five/grok/ftests/view/__init__.py
five/grok/ftests/view/argument.py
five/grok/ftests/view/association.py
five/grok/ftests/view/file.py
five/grok/ftests/view/index.py
five/grok/ftests/view/layers.py
five/grok/ftests/view/macros.py
five/grok/ftests/view/namespace.py
five/grok/ftests/view/namespace_override.py
five/grok/ftests/view/redirect.py
five/grok/ftests/view/test.pt
five/grok/ftests/view/view.py
five/grok/ftests/view/zope2_template.pt
five/grok/ftests/view/association_templates/painting.pt
five/grok/ftests/view/namespace_override_templates/index.pt
five/grok/ftests/view/static/style.css
five/grok/ftests/view/static/template.pt
five/grok/ftests/viewlet/__init__.py
five/grok/ftests/viewlet/manager_render.py
five/grok/ftests/viewlet/manager_template.py
five/grok/ftests/viewlet/security.py
five.grok-3.0.dist-info/LICENSE.txt
five.grok-3.0.dist-info/METADATA
five.grok-3.0.dist-info/WHEEL
five.grok-3.0.dist-info/namespace_packages.txt
five.grok-3.0.dist-info/top_level.txt
five.grok-3.0.dist-info/RECORD
