Metadata-Version: 2.1
Name: five.grok
Version: 3.0
Summary: Grok-like layer for Zope
Home-page: https://github.com/zopefoundation/five.grok
Author: Lennart Regebro, Godefroid Chapelle
Author-email: zope-dev@zope.dev
License: ZPL
Keywords: zope grok
Classifier: Environment :: Web Environment
Classifier: Intended Audience :: Developers
Classifier: License :: OSI Approved :: Zope Public License
Classifier: Programming Language :: Python
Classifier: Topic :: Software Development :: Libraries :: Python Modules
Classifier: Framework :: Zope :: 5
Classifier: Programming Language :: Python :: 3.7
Classifier: Programming Language :: Python :: 3.8
Classifier: Programming Language :: Python :: 3.9
Classifier: Programming Language :: Python :: 3.10
Classifier: Programming Language :: Python :: 3.11
Requires-Python: >=3.7
License-File: LICENSE.txt
Requires-Dist: setuptools
Requires-Dist: martian
Requires-Dist: Zope (>=4)
Requires-Dist: five.localsitemanager (>=2.0)
Requires-Dist: grokcore.annotation
Requires-Dist: grokcore.component (>=2.5)
Requires-Dist: grokcore.security (>=1.6.1)
Requires-Dist: grokcore.site
Requires-Dist: grokcore.view (>=1.12.1)
Requires-Dist: grokcore.viewlet (>=1.3)
Requires-Dist: zope.annotation
Requires-Dist: zope.component
Requires-Dist: zope.container
Requires-Dist: zope.contentprovider
Requires-Dist: zope.interface
Requires-Dist: zope.location
Requires-Dist: zope.pagetemplate
Requires-Dist: zope.publisher
Requires-Dist: zope.traversing
Provides-Extra: form
Requires-Dist: grokcore.formlib (>=1.4) ; extra == 'form'
Requires-Dist: five.formlib ; extra == 'form'
Requires-Dist: zope.formlib ; extra == 'form'
Provides-Extra: layout
Requires-Dist: grokcore.layout ; extra == 'layout'
Provides-Extra: test
Requires-Dist: grokcore.formlib (>=1.4) ; extra == 'test'
Requires-Dist: five.formlib ; extra == 'test'
Requires-Dist: zope.formlib ; extra == 'test'
Requires-Dist: grokcore.layout ; extra == 'test'
